LICENSE
README.md
pyproject.toml
src/mmisp/api/__init__.py
src/mmisp/api/auth.py
src/mmisp/api/config.py
src/mmisp/api/entry.py
src/mmisp/api/error.py
src/mmisp/api/exception_handler.py
src/mmisp/api/main.py
src/mmisp/api/middleware.py
src/mmisp/api/profile_middleware.py
src/mmisp/api/py.typed
src/mmisp/api/workflow.py
src/mmisp/api/routers/__init__.py
src/mmisp/api/routers/attributes.py
src/mmisp/api/routers/auth_keys.py
src/mmisp/api/routers/authentication.py
src/mmisp/api/routers/events.py
src/mmisp/api/routers/feeds.py
src/mmisp/api/routers/galaxies.py
src/mmisp/api/routers/galaxies_cluster.py
src/mmisp/api/routers/jobs.py
src/mmisp/api/routers/logs.py
src/mmisp/api/routers/noticelists.py
src/mmisp/api/routers/object_templates.py
src/mmisp/api/routers/objects.py
src/mmisp/api/routers/organisations.py
src/mmisp/api/routers/roles.py
src/mmisp/api/routers/servers.py
src/mmisp/api/routers/sharing_groups.py
src/mmisp/api/routers/sightings.py
src/mmisp/api/routers/statistics.py
src/mmisp/api/routers/tags.py
src/mmisp/api/routers/taxonomies.py
src/mmisp/api/routers/test_endpoints.py
src/mmisp/api/routers/user_settings.py
src/mmisp/api/routers/users.py
src/mmisp/api/routers/warninglists.py
src/mmisp/api/routers/worker.py
src/mmisp/api/routers/workflow.py
src/mmisp_api.egg-info/PKG-INFO
src/mmisp_api.egg-info/SOURCES.txt
src/mmisp_api.egg-info/dependency_links.txt
src/mmisp_api.egg-info/entry_points.txt
src/mmisp_api.egg-info/requires.txt
src/mmisp_api.egg-info/top_level.txt
tests/tests_db_access.py