Metadata-Version: 2.4
Name: mmisp-api
Version: 0.10.2
Requires-Python: >=3.11.0
License-File: LICENSE
Requires-Dist: mmisp-lib==0.11.3
Requires-Dist: fastapi==0.115.11
Requires-Dist: uvicorn[standard]==0.24.0.post1
Requires-Dist: python-dotenv==1.0.0
Requires-Dist: PyJWT==2.8.0
Requires-Dist: httpx==0.26.0
Requires-Dist: argon2-cffi==23.1.0
Requires-Dist: bcrypt==4.1.2
Requires-Dist: nanoid==2.0.0
Requires-Dist: cryptography==42.0.5
Requires-Dist: python-multipart==0.0.9
Requires-Dist: orjson
Provides-Extra: dev
Requires-Dist: pre-commit==3.6.0; extra == "dev"
Requires-Dist: pytest==8.3.5; extra == "dev"
Requires-Dist: pytest-asyncio==0.26.0; extra == "dev"
Requires-Dist: pytest-cov==4.1.0; extra == "dev"
Requires-Dist: respx==0.20.2; extra == "dev"
Requires-Dist: mysql-connector-python==8.3.0; extra == "dev"
Requires-Dist: icecream; extra == "dev"
Requires-Dist: types-Pygments; extra == "dev"
Requires-Dist: deepdiff==8.4.2; extra == "dev"
Requires-Dist: pyinstrument; extra == "dev"
Requires-Dist: twine; extra == "dev"
Requires-Dist: build; extra == "dev"
Provides-Extra: lint
Requires-Dist: ruff>=0.3.7; extra == "lint"
Requires-Dist: mypy==1.10.0; extra == "lint"
Provides-Extra: granian
Requires-Dist: granian; extra == "granian"
Provides-Extra: gunicorn
Requires-Dist: gunicorn; extra == "gunicorn"
Requires-Dist: uvicorn-worker; extra == "gunicorn"
Dynamic: license-file
